fds/__init__.py
fds/sdk/__init__.py
fds/sdk/DocumentsDistributorCallStreetEvents/__init__.py
fds/sdk/DocumentsDistributorCallStreetEvents/api_client.py
fds/sdk/DocumentsDistributorCallStreetEvents/configuration.py
fds/sdk/DocumentsDistributorCallStreetEvents/exceptions.py
fds/sdk/DocumentsDistributorCallStreetEvents/model_utils.py
fds/sdk/DocumentsDistributorCallStreetEvents/rest.py
fds/sdk/DocumentsDistributorCallStreetEvents/api/__init__.py
fds/sdk/DocumentsDistributorCallStreetEvents/api/events_audio_api.py
fds/sdk/DocumentsDistributorCallStreetEvents/api/near_real_time_transcripts_api.py
fds/sdk/DocumentsDistributorCallStreetEvents/apis/__init__.py
fds/sdk/DocumentsDistributorCallStreetEvents/model/__init__.py
fds/sdk/DocumentsDistributorCallStreetEvents/model/error.py
fds/sdk/DocumentsDistributorCallStreetEvents/model/events_audio.py
fds/sdk/DocumentsDistributorCallStreetEvents/model/events_audio400_response.py
fds/sdk/DocumentsDistributorCallStreetEvents/model/events_audio400_response_details.py
fds/sdk/DocumentsDistributorCallStreetEvents/model/events_audio400_response_details_valid_parameters.py
fds/sdk/DocumentsDistributorCallStreetEvents/model/events_audio_data.py
fds/sdk/DocumentsDistributorCallStreetEvents/model/events_audio_history.py
fds/sdk/DocumentsDistributorCallStreetEvents/model/events_audio_history400_response.py
fds/sdk/DocumentsDistributorCallStreetEvents/model/events_audio_history400_response_details.py
fds/sdk/DocumentsDistributorCallStreetEvents/model/events_audio_history400_response_details_valid_parameters.py
fds/sdk/DocumentsDistributorCallStreetEvents/model/events_audio_history_data.py
fds/sdk/DocumentsDistributorCallStreetEvents/model/events_audio_history_meta.py
fds/sdk/DocumentsDistributorCallStreetEvents/model/events_audio_meta.py
fds/sdk/DocumentsDistributorCallStreetEvents/model/events_audio_meta_pagination.py
fds/sdk/DocumentsDistributorCallStreetEvents/model/indexed_nrt.py
fds.sdk.DocumentsDistributorCallStreetEvents-0.21.20.dist-info/LICENSE
fds.sdk.DocumentsDistributorCallStreetEvents-0.21.20.dist-info/METADATA
fds.sdk.DocumentsDistributorCallStreetEvents-0.21.20.dist-info/WHEEL
fds.sdk.DocumentsDistributorCallStreetEvents-0.21.20.dist-info/top_level.txt
fds.sdk.DocumentsDistributorCallStreetEvents-0.21.20.dist-info/RECORD
